<?xml version="1.0" encoding="UTF-8"?>
<con:soapui-project id="fe6cb0dc-1ddd-470e-9449-ebdd14c6316b" activeEnvironment="Default" name="National static committee" resourceRoot="${projectDir}" soapui-version="5.4.0" abortOnError="false" runType="SEQUENTIAL" xmlns:con="http://eviware.com/soapui/config"><con:settings/><con:interface xsi:type="con:RestService" id="e344cd5a-72cb-431b-a801-20fd721f368f" wadlVersion="http://wadl.dev.java.net/2009/02" name="http://vm-wildfly.todes.by:8181" type="rest" xmlns:xsi="http://www.w3.org/2001/XMLSchema-instance"><con:settings/><con:definitionCache/><con:endpoints><con:endpoint>http://vm-wildfly.todes.by:8181</con:endpoint></con:endpoints><con:resource name="get Persons by regDate" path="/cxf/statcommit/data" id="3363334b-437a-4be8-bf4c-89ea938fd054"><con:settings/><con:parameters><con:parameter><con:name>typeForm</con:name><con:value>0</con:value><con:style>QUERY</con:style><con:default>0</con:default><con:path xsi:nil="true"/><con:description xsi:nil="true"/></con:parameter><con:parameter><con:name>since</con:name><con:value>01.01.1991</con:value><con:style>QUERY</con:style><con:default>01.01.1991</con:default><con:path xsi:nil="true"/><con:description xsi:nil="true"/></con:parameter><con:parameter><con:name>till</con:name><con:value>01.05.1995</con:value><con:style>QUERY</con:style><con:default>01.05.1995</con:default><con:path xsi:nil="true"/><con:description xsi:nil="true"/></con:parameter></con:parameters><con:method name="Data" id="4909a28e-3c79-4d70-99b1-4781f88b5f3c" method="GET"><con:description>Найти person в таблице docsetdata где в её связной таблице form19_20 regdate равен с..по и typeForm тип формы(0-прибыл,1-убыл)</con:description><con:settings/><con:parameters/><con:representation type="RESPONSE"><con:mediaType>application/json</con:mediaType><con:status>200</con:status><con:params/><con:element>Response</con:element></con:representation><con:request name="get persons by regdate" id="eb7efa9f-8bf0-43d4-978a-53399a195c79" mediaType="application/json"><con:settings><con:setting id="com.eviware.soapui.impl.wsdl.WsdlRequest@request-headers">&lt;xml-fragment/></con:setting></con:settings><con:encoding>UTF-8</con:encoding><con:endpoint>http://vm-wildfly.todes.by:8181</con:endpoint><con:request/><con:originalUri>http://vm-wildfly.todes.by/cxf/statcommit/data</con:originalUri><con:credentials><con:authType>No Authorization</con:authType></con:credentials><con:jmsConfig JMSDeliveryMode="PERSISTENT"/><con:jmsPropertyConfig/><con:parameters>
  <con:entry key="since" value="01.01.1991"/>
  <con:entry key="typeForm" value="0"/>
  <con:entry key="till" value="01.05.1995"/>
</con:parameters><con:parameterOrder><con:entry>typeForm</con:entry><con:entry>since</con:entry><con:entry>till</con:entry></con:parameterOrder></con:request></con:method></con:resource></con:interface><con:properties/><con:wssContainer/><con:oAuth2ProfileContainer/><con:oAuth1ProfileContainer/></con:soapui-project>